[{"stop_lat": 30.280661, "stop_lon": -97.733899, "route_id": "18", "stop_url": "http://www.capmetro.org/gismaps/stops/1181.html", "stop_id": "1181", "stop_desc": "Northwest corner of SAN JACINTO and TRINITY - Mid-Block", "stop_name": "1960 SAN JACINTO/TRINITY"}, {"stop_lat": 30.289983, "stop_lon": -97.7712, "route_id": "18", "stop_url": "http://www.capmetro.org/gismaps/stops/1440.html", "stop_id": "1440", "stop_desc": "Southeast corner of ENFIELD and NORWALK - Farside", "stop_name": "2525 ENFIELD/NORWALK"}, {"stop_lat": 30.284786, "stop_lon": -97.762233, "route_id": "18", "stop_url": "http://www.capmetro.org/gismaps/stops/1444.html", "stop_id": "1444", "stop_desc": "Southwest corner of ENFIELD and HARTFORD - Nearside", "stop_name": "1801 ENFIELD/HARTFORD"}, {"stop_lat": 30.282771, "stop_lon": -97.758105, "route_id": "18", "stop_url": "http://www.capmetro.org/gismaps/stops/1446.html", "stop_id": "1446", "stop_desc": "Southwest corner of ENFIELD and WEST LYNN - Nearside", "stop_name": "1603 ENFIELD/WEST LYNN"}, {"stop_lat": 30.279978, "stop_lon": -97.758783, "route_id": "18", "stop_url": "http://www.capmetro.org/gismaps/stops/1448.html", "stop_id": "1448", "stop_desc": "Southwest corner of 12TH and EASON - Nearside", "stop_name": "12TH/EASON"}, {"stop_lat": 30.277843, "stop_lon": -97.754367, "route_id": "18", "stop_url": "http://www.capmetro.org/gismaps/stops/1450.html", "stop_id": "1450", "stop_desc": "Southwest corner of 12TH and BLANCO - Nearside", "stop_name": "1201 12TH/BLANCO"}, {"stop_lat": 30.276845, "stop_lon": -97.751568, "route_id": "18", "stop_url": "http://www.capmetro.org/gismaps/stops/1451.html", "stop_id": "1451", "stop_desc": "Southwest corner of 12TH and LAMAR - Nearside", "stop_name": "1001 12TH/LAMAR"}, {"stop_lat": 30.27571, "stop_lon": -97.747549, "route_id": "18", "stop_url": "http://www.capmetro.org/gismaps/stops/1453.html", "stop_id": "1453", "stop_desc": "Southwest corner of 12TH and RIO GRANDE - Nearside", "stop_name": "701 12TH/RIO GRANDE"}, {"stop_lat": 30.277993, "stop_lon": -97.754392, "route_id": "18", "stop_url": "http://www.capmetro.org/gismaps/stops/1507.html", "stop_id": "1507", "stop_desc": "Northwest corner of 12TH and WINDSOR - Farside", "stop_name": "1200 12TH/WINDSOR"}, {"stop_lat": 30.283102, "stop_lon": -97.758934, "route_id": "18", "stop_url": "http://www.capmetro.org/gismaps/stops/1511.html", "stop_id": "1511", "stop_desc": "Northeast corner of ENFIELD and PEASE - Nearside", "stop_name": "ENFIELD/PEASE"}, {"stop_lat": 30.28462, "stop_lon": -97.761717, "route_id": "18", "stop_url": "http://www.capmetro.org/gismaps/stops/1513.html", "stop_id": "1513", "stop_desc": "Northeast corner of ENFIELD and HARTFORD - Nearside", "stop_name": "1728 ENFIELD/HARTFORD"}, {"stop_lat": 30.29028, "stop_lon": -97.771413, "route_id": "18", "stop_url": "http://www.capmetro.org/gismaps/stops/1517.html", "stop_id": "1517", "stop_desc": "Northwest corner of ENFIELD and NORWALK - Farside", "stop_name": "2600 ENFIELD/NORWALK"}, {"stop_lat": 30.292411, "stop_lon": -97.775684, "route_id": "18", "stop_url": "http://www.capmetro.org/gismaps/stops/1519.html", "stop_id": "1519", "stop_desc": "Northwest corner of ENFIELD and HOPI - Farside", "stop_name": "ENFIELD/HOPI"}, {"stop_lat": 30.285795, "stop_lon": -97.774994, "route_id": "18", "stop_url": "http://www.capmetro.org/gismaps/stops/1983.html", "stop_id": "1983", "stop_desc": "Northeast corner of EXPOSITION and 10TH - Farside", "stop_name": "EXPOSITION/10TH"}, {"stop_lat": 30.28766, "stop_lon": -97.773815, "route_id": "18", "stop_url": "http://www.capmetro.org/gismaps/stops/1984.html", "stop_id": "1984", "stop_desc": "Southeast corner of EXPOSITION and 12TH - Nearside", "stop_name": "EXPOSITION/12TH"}, {"stop_lat": 30.290414, "stop_lon": -97.772089, "route_id": "18", "stop_url": "http://www.capmetro.org/gismaps/stops/1985.html", "stop_id": "1985", "stop_desc": "Southeast corner of EXPOSITION and ENFIELD - Nearside", "stop_name": "EXPOSITION/ENFIELD SE CORNER"}, {"stop_lat": 30.275022, "stop_lon": -97.744169, "route_id": "18", "stop_url": "http://www.capmetro.org/gismaps/stops/2738.html", "stop_id": "2738", "stop_desc": "Northwest corner of GUADALUPE and 12TH - Nearside", "stop_name": "CAPITOL STATION (SB)"}, {"stop_lat": 30.279309, "stop_lon": -97.732951, "route_id": "18", "stop_url": "http://www.capmetro.org/gismaps/stops/2761.html", "stop_id": "2761", "stop_desc": "Northwest corner of MARTIN LUTHER KING and RED RIVER - Farside", "stop_name": "500 MARTIN LUTHER KING/RED RIVER"}, {"stop_lat": 30.279262, "stop_lon": -97.733535, "route_id": "18", "stop_url": "http://www.capmetro.org/gismaps/stops/2768.html", "stop_id": "2768", "stop_desc": "Southeast corner of MARTIN LUTHER KING and TRINITY - Mid-Block", "stop_name": "MARTIN LUTHER KING/TRINITY MIDBLOCK"}, {"stop_lat": 30.2834, "stop_lon": -97.7377, "route_id": "18", "stop_url": "http://www.capmetro.org/gismaps/stops/3494.html", "stop_id": "3494", "stop_desc": "Southwest corner of 21ST and SPEEDWAY - Nearside", "stop_name": "SPEEDWAY / 21ST"}, {"stop_lat": 30.283679, "stop_lon": -97.74128, "route_id": "18", "stop_url": "http://www.capmetro.org/gismaps/stops/4095.html", "stop_id": "4095", "stop_desc": "Southwest corner of 21ST and WHITIS - Mid-Block", "stop_name": "21ST/WHITIS (DOBIE MALL)"}, {"stop_lat": 30.280391, "stop_lon": -97.733978, "route_id": "18", "stop_url": "http://www.capmetro.org/gismaps/stops/4134.html", "stop_id": "4134", "stop_desc": "Northeast corner of SAN JACINTO and TRINITY - Farside", "stop_name": "1951 SAN JACINTO/TRINITY"}, {"stop_lat": 30.283311, "stop_lon": -97.734547, "route_id": "18", "stop_url": "http://www.capmetro.org/gismaps/stops/4136.html", "stop_id": "4136", "stop_desc": "Northwest corner of 21ST and SAN JACINTO - Mid-Block", "stop_name": "300 21ST/SAN JACINTO"}, {"stop_lat": 30.283127, "stop_lon": -97.734394, "route_id": "18", "stop_url": "http://www.capmetro.org/gismaps/stops/4137.html", "stop_id": "4137", "stop_desc": "Southwest corner of 21ST and SAN JACINTO - Nearside", "stop_name": "309 21ST/SAN JACINTO"}, {"stop_lat": 30.287548, "stop_lon": -97.766813, "route_id": "18", "stop_url": "http://www.capmetro.org/gismaps/stops/4157.html", "stop_id": "4157", "stop_desc": "Northwest corner of ENFIELD and MERIDEN - Mid-Block", "stop_name": "2206 ENFIELD/MERIDEN"}, {"stop_lat": 30.28741, "stop_lon": -97.76683, "route_id": "18", "stop_url": "http://www.capmetro.org/gismaps/stops/4158.html", "stop_id": "4158", "stop_desc": "Southeast corner of ENFIELD and KENT - Mid-Block", "stop_name": "2207 ENFIELD/KENT"}, {"stop_lat": 30.283626, "stop_lon": -97.776386, "route_id": "18", "stop_url": "http://www.capmetro.org/gismaps/stops/4161.html", "stop_id": "4161", "stop_desc": "Northeast corner of EXPOSITION and LAKE AUSTIN - Mid-Block", "stop_name": "715 EXPOSITION/LAKE AUSTIN"}, {"stop_lat": 30.278682, "stop_lon": -97.72723, "route_id": "18", "stop_url": "http://www.capmetro.org/gismaps/stops/4183.html", "stop_id": "4183", "stop_desc": "Southeast corner of MARTIN LUTHER KING and IH 35 - Mid-Block", "stop_name": "1255 MARTIN LUTHER KING/IH 35"}, {"stop_lat": 30.282537, "stop_lon": -97.703456, "route_id": "18", "stop_url": "http://www.capmetro.org/gismaps/stops/4195.html", "stop_id": "4195", "stop_desc": "Southeast corner of MARTIN LUTHER KING and AIRPORT - Farside", "stop_name": "3205 MARTIN LUTHER KING/AIRPORT"}, {"stop_lat": 30.282553, "stop_lon": -97.704518, "route_id": "18", "stop_url": "http://www.capmetro.org/gismaps/stops/4196.html", "stop_id": "4196", "stop_desc": "Northwest corner of MARTIN LUTHER KING and AIRPORT - Farside", "stop_name": "3014 MARTIN LUTHER KING/AIRPORT"}, {"stop_lat": 30.279665, "stop_lon": -97.73431, "route_id": "18", "stop_url": "http://www.capmetro.org/gismaps/stops/4586.html", "stop_id": "4586", "stop_desc": "Northeast corner of MARTIN LUTHER KING and TRINITY - Nearside", "stop_name": "400 MARTIN LUTHER KING/TRINITY"}, {"stop_lat": 30.286309, "stop_lon": -97.678798, "route_id": "18", "stop_url": "http://www.capmetro.org/gismaps/stops/4602.html", "stop_id": "4602", "stop_desc": "Northwest corner of MARTIN LUTHER KING and SCOTTSDALE - Farside", "stop_name": "MARTIN LUTHER KING/SCOTTSDALE"}, {"stop_lat": 30.285131, "stop_lon": -97.687713, "route_id": "18", "stop_url": "http://www.capmetro.org/gismaps/stops/4603.html", "stop_id": "4603", "stop_desc": "Northeast corner of MARTIN LUTHER KING and TEMPLE - Nearside", "stop_name": "MARTIN LUTHER KING/TEMPLE"}, {"stop_lat": 30.283384, "stop_lon": -97.742081, "route_id": "18", "stop_url": "http://www.capmetro.org/gismaps/stops/498.html", "stop_id": "498", "stop_desc": "Southwest corner of GUADALUPE and 21ST - Mid-Block", "stop_name": "GUADALUPE/W. 21ST STREET"}, {"stop_lat": 30.283973, "stop_lon": -97.671344, "route_id": "18", "stop_url": "http://www.capmetro.org/gismaps/stops/5007.html", "stop_id": "5007", "stop_desc": "Southeast corner of TANNEHILL and WEBBERVILLE - Mid-Block", "stop_name": "TANNEHILL/WEBBERVILLE"}, {"stop_lat": 30.278962, "stop_lon": -97.742708, "route_id": "18", "stop_url": "http://www.capmetro.org/gismaps/stops/501.html", "stop_id": "501", "stop_desc": "Northwest corner of GUADALUPE and 16TH - Nearside", "stop_name": "GUADALUPE/16TH STREET"}, {"stop_lat": 30.283861, "stop_lon": -97.741353, "route_id": "18", "stop_url": "http://www.capmetro.org/gismaps/stops/5179.html", "stop_id": "5179", "stop_desc": "Northwest corner of 21ST and WHITIS - Mid-Block", "stop_name": "300 21ST/WHITIS"}, {"stop_lat": 30.283493, "stop_lon": -97.737156, "route_id": "18", "stop_url": "http://www.capmetro.org/gismaps/stops/5207.html", "stop_id": "5207", "stop_desc": "Northeast corner of 21ST and SPEEDWAY - Nearside", "stop_name": "21ST/SPEEDWAY"}, {"stop_lat": 30.280356, "stop_lon": -97.718217, "route_id": "18", "stop_url": "http://www.capmetro.org/gismaps/stops/5492.html", "stop_id": "5492", "stop_desc": "Northeast corner of MARTIN LUTHER KING and COLETO - Nearside", "stop_name": "2200 MARTIN LUTHER KING/COLETO"}, {"stop_lat": 30.284893, "stop_lon": -97.688314, "route_id": "18", "stop_url": "http://www.capmetro.org/gismaps/stops/5570.html", "stop_id": "5570", "stop_desc": "Southeast corner of MARTIN LUTHER KING and WILDROSE - Farside", "stop_name": "MARTIN LUTHER KING/WILDROSE"}, {"stop_lat": 30.283767, "stop_lon": -97.696791, "route_id": "18", "stop_url": "http://www.capmetro.org/gismaps/stops/5571.html", "stop_id": "5571", "stop_desc": "Northwest corner of MARTIN LUTHER KING and E M FRANKLIN - Farside", "stop_name": "3520 MARTIN LUTHER KING/EM FRANKLIN"}, {"stop_lat": 30.278688, "stop_lon": -97.731471, "route_id": "18", "stop_url": "http://www.capmetro.org/gismaps/stops/5624.html", "stop_id": "5624", "stop_desc": "Southeast corner of MARTIN LUTHER KING and RED RIVER - Mid-Block", "stop_name": "MARTIN LUTHER KING/RED RIVER"}, {"stop_lat": 30.285183, "stop_lon": -97.681314, "route_id": "18", "stop_url": "http://www.capmetro.org/gismaps/stops/5636.html", "stop_id": "5636", "stop_desc": "Southeast corner of HEFLIN and SPRINGDALE - Farside", "stop_name": "4705 HEFLIN/SPRINGDALE"}, {"stop_lat": 30.28301, "stop_lon": -97.674479, "route_id": "18", "stop_url": "http://www.capmetro.org/gismaps/stops/5637.html", "stop_id": "5637", "stop_desc": "Southeast corner of WEBBERVILLE and STONE GATE - Farside", "stop_name": "1913 WEBBERVILLE/STONE GATE"}, {"stop_lat": 30.286729, "stop_lon": -97.671079, "route_id": "18", "stop_url": "http://www.capmetro.org/gismaps/stops/5640.html", "stop_id": "5640", "stop_desc": "Northeast corner of MARTIN LUTHER KING and HILLDALE - Nearside", "stop_name": "MARTIN LUTHER KING/HILLDALE"}, {"stop_lat": 30.286744, "stop_lon": -97.674512, "route_id": "18", "stop_url": "http://www.capmetro.org/gismaps/stops/5641.html", "stop_id": "5641", "stop_desc": "Northeast corner of MARTIN LUTHER KING and OLDFORT HILL - Nearside", "stop_name": "MARTIN LUTHER KING/OLDFORT HILL"}, {"stop_lat": 30.28262, "stop_lon": -97.676905, "route_id": "18", "stop_url": "http://www.capmetro.org/gismaps/stops/5642.html", "stop_id": "5642", "stop_desc": "Northwest corner of HEFLIN and WEBBERVILLE - Nearside", "stop_name": "5107 HEFLIN/WEBBERVILLE"}, {"stop_lat": 30.288533, "stop_lon": -97.780899, "route_id": "18", "stop_url": "http://www.capmetro.org/gismaps/stops/5723.html", "stop_id": "5723", "stop_desc": "Southwest corner of LAKE AUSTIN and LUFKIN - Nearside", "stop_name": "3450 LAKE AUSTIN/LUFKIN"}, {"stop_lat": 30.280125, "stop_lon": -97.758835, "route_id": "18", "stop_url": "http://www.capmetro.org/gismaps/stops/5737.html", "stop_id": "5737", "stop_desc": "Northeast corner of 12TH and WEST LYNN - Nearside", "stop_name": "1505 12TH/WEST LYNN"}, {"stop_lat": 30.295668, "stop_lon": -97.783853, "route_id": "18", "stop_url": "http://www.capmetro.org/gismaps/stops/5740.html", "stop_id": "5740", "stop_desc": "Southwest corner of LAKE AUSTIN and ENFIELD - Farside", "stop_name": "3825 LAKE AUSTIN/ENFIELD"}, {"stop_lat": 30.294345, "stop_lon": -97.779805, "route_id": "18", "stop_url": "http://www.capmetro.org/gismaps/stops/5754.html", "stop_id": "5754", "stop_desc": "Northeast corner of ENFIELD and ROBINHOOD - Nearside", "stop_name": "3418 ENFIELD/ROBINHOOD"}, {"stop_lat": 30.276753, "stop_lon": -97.750729, "route_id": "18", "stop_url": "http://www.capmetro.org/gismaps/stops/5756.html", "stop_id": "5756", "stop_desc": "Northeast corner of 12TH and LAMAR - Mid-Block", "stop_name": "915 12TH/LAMAR"}, {"stop_lat": 30.282033, "stop_lon": -97.70768, "route_id": "18", "stop_url": "http://www.capmetro.org/gismaps/stops/5786.html", "stop_id": "5786", "stop_desc": "Northeast corner of MARTIN LUTHER KING and CLIFFORD - Mid-Block", "stop_name": "MARTIN LUTHER KING/CLIFFORD"}, {"stop_lat": 30.275943, "stop_lon": -97.74761, "route_id": "18", "stop_url": "http://www.capmetro.org/gismaps/stops/5787.html", "stop_id": "5787", "stop_desc": "Northwest corner of 12TH and RIO GRANDE - Farside", "stop_name": "700 12TH/RIO GRANDE"}, {"stop_lat": 30.281684, "stop_lon": -97.709892, "route_id": "18", "stop_url": "http://www.capmetro.org/gismaps/stops/5801.html", "stop_id": "5801", "stop_desc": "Northwest corner of MARTIN LUTHER KING and ALEXANDER - Farside", "stop_name": "MARTIN LUTHER KING/ALEXANDER"}, {"stop_lat": 30.281548, "stop_lon": -97.709813, "route_id": "18", "stop_url": "http://www.capmetro.org/gismaps/stops/5802.html", "stop_id": "5802", "stop_desc": "Southwest corner of MARTIN LUTHER KING and ALEXANDER - Nearside", "stop_name": "MARTIN LUTHER KING/ALEXANDER"}, {"stop_lat": 30.275587, "stop_lon": -97.742558, "route_id": "18", "stop_url": "http://www.capmetro.org/gismaps/stops/591.html", "stop_id": "591", "stop_desc": "Southeast corner of LAVACA and 13TH - Nearside", "stop_name": "CAPITOL STATION (NB)"}, {"stop_lat": 30.277383, "stop_lon": -97.741894, "route_id": "18", "stop_url": "http://www.capmetro.org/gismaps/stops/593.html", "stop_id": "593", "stop_desc": "Southeast corner of LAVACA and 15TH - Nearside", "stop_name": "LAVACA/15TH"}, {"stop_lat": 30.278834, "stop_lon": -97.741358, "route_id": "18", "stop_url": "http://www.capmetro.org/gismaps/stops/5940.html", "stop_id": "5940", "stop_desc": "Southeast corner of LAVACA and 17TH - Mid-Block", "stop_name": "1609 LAVACA/17TH (MB)"}, {"stop_lat": 30.282583, "stop_lon": -97.741932, "route_id": "18", "stop_url": "http://www.capmetro.org/gismaps/stops/596.html", "stop_id": "596", "stop_desc": "Southeast corner of GUADALUPE and 20TH - Nearside", "stop_name": "GUADALUPE/20TH"}, {"stop_lat": 30.279074, "stop_lon": -97.724701, "route_id": "18", "stop_url": "http://www.capmetro.org/gismaps/stops/870.html", "stop_id": "870", "stop_desc": "Southeast corner of MARTIN LUTHER KING and COMAL - Farside", "stop_name": "1509 MARTIN LUTHER KING/COMAL"}, {"stop_lat": 30.279406, "stop_lon": -97.722844, "route_id": "18", "stop_url": "http://www.capmetro.org/gismaps/stops/871.html", "stop_id": "871", "stop_desc": "Southeast corner of MARTIN LUTHER KING and LEONA - Farside", "stop_name": "1703 MARTIN LUTHER KING/LEONA"}, {"stop_lat": 30.279695, "stop_lon": -97.721372, "route_id": "18", "stop_url": "http://www.capmetro.org/gismaps/stops/872.html", "stop_id": "872", "stop_desc": "Southwest corner of MARTIN LUTHER KING and CHICON - Nearside", "stop_name": "1813 MARTIN LUTHER KING/CHICON"}, {"stop_lat": 30.28023, "stop_lon": -97.718137, "route_id": "18", "stop_url": "http://www.capmetro.org/gismaps/stops/873.html", "stop_id": "873", "stop_desc": "Southeast corner of MARTIN LUTHER KING and FERDINAND - Farside", "stop_name": "2207 MARTIN LUTHER KING/FERDINAND"}, {"stop_lat": 30.280586, "stop_lon": -97.715949, "route_id": "18", "stop_url": "http://www.capmetro.org/gismaps/stops/874.html", "stop_id": "874", "stop_desc": "Southeast corner of MARTIN LUTHER KING and MAPLE - Farside", "stop_name": "2401 MARTIN LUTHER KING/MAPLE"}, {"stop_lat": 30.280972, "stop_lon": -97.713458, "route_id": "18", "stop_url": "http://www.capmetro.org/gismaps/stops/875.html", "stop_id": "875", "stop_desc": "Southwest corner of MARTIN LUTHER KING and WALNUT - Nearside", "stop_name": "2615 MARTIN LUTHER KING/WALNUT"}, {"stop_lat": 30.281869, "stop_lon": -97.707799, "route_id": "18", "stop_url": "http://www.capmetro.org/gismaps/stops/877.html", "stop_id": "877", "stop_desc": "Southwest corner of MARTIN LUTHER KING and CLIFFORD - Nearside", "stop_name": "2915 MARTIN LUTHER KING/CLIFFORD"}, {"stop_lat": 30.282207, "stop_lon": -97.70565, "route_id": "18", "stop_url": "http://www.capmetro.org/gismaps/stops/878.html", "stop_id": "878", "stop_desc": "Southwest corner of MARTIN LUTHER KING and HARVEY - Nearside", "stop_name": "2945 MARTIN LUTHER KING/HARVEY"}, {"stop_lat": 30.283318, "stop_lon": -97.698197, "route_id": "18", "stop_url": "http://www.capmetro.org/gismaps/stops/880.html", "stop_id": "880", "stop_desc": "Southeast corner of MARTIN LUTHER KING and GREENWOOD - Farside", "stop_name": "3431 MARTIN LUTHER KING/GREENWOOD"}, {"stop_lat": 30.283699, "stop_lon": -97.695712, "route_id": "18", "stop_url": "http://www.capmetro.org/gismaps/stops/881.html", "stop_id": "881", "stop_desc": "Southeast corner of MARTIN LUTHER KING and E M FRANKLIN - Farside", "stop_name": "3601 MARTIN LUTHER KING/EM FRANKLIN"}, {"stop_lat": 30.284091, "stop_lon": -97.693161, "route_id": "18", "stop_url": "http://www.capmetro.org/gismaps/stops/882.html", "stop_id": "882", "stop_desc": "Southwest corner of MARTIN LUTHER KING and PEREZ - Nearside", "stop_name": "3815 MARTIN LUTHER KING/PEREZ"}, {"stop_lat": 30.284442, "stop_lon": -97.690986, "route_id": "18", "stop_url": "http://www.capmetro.org/gismaps/stops/883.html", "stop_id": "883", "stop_desc": "Southeast corner of MARTIN LUTHER KING and ADRIANE - Farside", "stop_name": "4021 MARTIN LUTHER KING/ADRIANE"}, {"stop_lat": 30.28515, "stop_lon": -97.68658, "route_id": "18", "stop_url": "http://www.capmetro.org/gismaps/stops/885.html", "stop_id": "885", "stop_desc": "Southeast corner of MARTIN LUTHER KING and ASTOR - Farside", "stop_name": "4211 MARTIN LUTHER KING/ASTOR"}, {"stop_lat": 30.28569, "stop_lon": -97.68292, "route_id": "18", "stop_url": "http://www.capmetro.org/gismaps/stops/886.html", "stop_id": "886", "stop_desc": "Southwest corner of MARTIN LUTHER KING and SPRINGDALE - Nearside", "stop_name": "MARTIN LUTHER KING/SPRINGDALE"}, {"stop_lat": 30.285993, "stop_lon": -97.682245, "route_id": "18", "stop_url": "http://www.capmetro.org/gismaps/stops/898.html", "stop_id": "898", "stop_desc": "Northeast corner of MARTIN LUTHER KING and SPRINGDALE - Nearside", "stop_name": "4600 MARTIN LUTHER KING/SPRINGDALE"}, {"stop_lat": 30.285367, "stop_lon": -97.686178, "route_id": "18", "stop_url": "http://www.capmetro.org/gismaps/stops/899.html", "stop_id": "899", "stop_desc": "Northeast corner of MARTIN LUTHER KING and ASTOR - Nearside", "stop_name": "4214 MARTIN LUTHER KING/ASTOR"}, {"stop_lat": 30.284556, "stop_lon": -97.691402, "route_id": "18", "stop_url": "http://www.capmetro.org/gismaps/stops/901.html", "stop_id": "901", "stop_desc": "Northeast corner of MARTIN LUTHER KING and ADRIANE - Nearside", "stop_name": "4000 MARTIN LUTHER KING/ADRIANE"}, {"stop_lat": 30.284342, "stop_lon": -97.692951, "route_id": "18", "stop_url": "http://www.capmetro.org/gismaps/stops/902.html", "stop_id": "902", "stop_desc": "Northeast corner of MARTIN LUTHER KING and PEREZ - Nearside", "stop_name": "3900 MARTIN LUTHER KING/PEREZ"}, {"stop_lat": 30.283022, "stop_lon": -97.701544, "route_id": "18", "stop_url": "http://www.capmetro.org/gismaps/stops/905.html", "stop_id": "905", "stop_desc": "Northeast corner of MARTIN LUTHER KING and TILLERY - Nearside", "stop_name": "3300 MARTIN LUTHER KING/TILLERY"}, {"stop_lat": 30.28113, "stop_lon": -97.713317, "route_id": "18", "stop_url": "http://www.capmetro.org/gismaps/stops/909.html", "stop_id": "909", "stop_desc": "Northeast corner of MARTIN LUTHER KING and WALNUT - Nearside", "stop_name": "2700 MARTIN LUTHER KING/WALNUT"}, {"stop_lat": 30.280549, "stop_lon": -97.717136, "route_id": "18", "stop_url": "http://www.capmetro.org/gismaps/stops/910.html", "stop_id": "910", "stop_desc": "Northeast corner of MARTIN LUTHER KING and CHESTNUT - Nearside", "stop_name": "2300 MARTIN LUTHER KING/CHESTNUT"}, {"stop_lat": 30.279877, "stop_lon": -97.721101, "route_id": "18", "stop_url": "http://www.capmetro.org/gismaps/stops/911.html", "stop_id": "911", "stop_desc": "Northeast corner of MARTIN LUTHER KING and CHICON - Nearside", "stop_name": "1900 MARTIN LUTHER KING/CHICON"}, {"stop_lat": 30.279502, "stop_lon": -97.723095, "route_id": "18", "stop_url": "http://www.capmetro.org/gismaps/stops/912.html", "stop_id": "912", "stop_desc": "Northeast corner of MARTIN LUTHER KING and LEONA - Nearside", "stop_name": "1700 MARTIN LUTHER KING/LEONA"}, {"stop_lat": 30.279075, "stop_lon": -97.725602, "route_id": "18", "stop_url": "http://www.capmetro.org/gismaps/stops/913.html", "stop_id": "913", "stop_desc": "Northwest corner of MARTIN LUTHER KING and COMAL - Farside", "stop_name": "1498 MARTIN LUTHER KING/COMAL"}]
