[{"stop_lat": 30.157841, "stop_lon": -97.800157, "route_id": "201", "stop_url": "http://www.capmetro.org/gismaps/stops/4908.html", "stop_id": "4908", "stop_desc": "Northeast corner of 1ST and ISLAND OAK - Farside", "stop_name": "9200 SOUTH 1ST/ISLAND OAK"}, {"stop_lat": 30.171737, "stop_lon": -97.800185, "route_id": "201", "stop_url": "http://www.capmetro.org/gismaps/stops/4909.html", "stop_id": "4909", "stop_desc": "Southeast corner of 1ST and SLAUGHTER - Mid-Block", "stop_name": "9201 S 1ST/SLAUGHTER"}, {"stop_lat": 30.163367, "stop_lon": -97.791351, "route_id": "201", "stop_url": "http://www.capmetro.org/gismaps/stops/5263.html", "stop_id": "5263", "stop_desc": "Northeast corner of TURK and CULLEN - Mid-Block", "stop_name": "200 TURK/CULLEN"}, {"stop_lat": 30.176243, "stop_lon": -97.784118, "route_id": "201", "stop_url": "http://www.capmetro.org/gismaps/stops/5310.html", "stop_id": "5310", "stop_desc": "Southeast corner of CONGRESS and FOREMOST - Mid-Block", "stop_name": "8201 CONGRESS/FOREMOST"}, {"stop_lat": 30.176853, "stop_lon": -97.784179, "route_id": "201", "stop_url": "http://www.capmetro.org/gismaps/stops/5311.html", "stop_id": "5311", "stop_desc": "Southwest corner of CONGRESS and FOREMOST - Mid-Block", "stop_name": "8200 CONGRESS/FOREMOST"}, {"stop_lat": 30.191866, "stop_lon": -97.779364, "route_id": "201", "stop_url": "http://www.capmetro.org/gismaps/stops/5312.html", "stop_id": "5312", "stop_desc": "Northwest corner of CONGRESS and CLEARDAY - Nearside", "stop_name": "6800 CONGRESS/CLEARDAY"}, {"stop_lat": 30.190842, "stop_lon": -97.779568, "route_id": "201", "stop_url": "http://www.capmetro.org/gismaps/stops/5313.html", "stop_id": "5313", "stop_desc": "Northeast corner of CONGRESS and CLEARDAY - Nearside", "stop_name": "6811 CONGRESS/CLEARDAY"}, {"stop_lat": 30.186, "stop_lon": -97.781105, "route_id": "201", "stop_url": "http://www.capmetro.org/gismaps/stops/5314.html", "stop_id": "5314", "stop_desc": "Northeast corner of CONGRESS and DITTMAR - Mid-Block", "stop_name": "7309 CONGRESS/DITTMAR"}, {"stop_lat": 30.185789, "stop_lon": -97.781306, "route_id": "201", "stop_url": "http://www.capmetro.org/gismaps/stops/5315.html", "stop_id": "5315", "stop_desc": "Northwest corner of CONGRESS and DITTMAR - Mid-Block", "stop_name": "7310 CONGRESS/DITTMAR"}, {"stop_lat": 30.189947, "stop_lon": -97.767587, "route_id": "201", "stop_url": "http://www.capmetro.org/gismaps/stops/5377.html", "stop_id": "5377", "stop_desc": "Northwest corner of BLUFF SPRINGS and WILLIAM CANNON - Mid-Block", "stop_name": "6502 BLUFF SPRINGS/WILLIAM CANNON"}, {"stop_lat": 30.166936, "stop_lon": -97.790926, "route_id": "201", "stop_url": "http://www.capmetro.org/gismaps/stops/5378.html", "stop_id": "5378", "stop_desc": "Southeast corner of CULLEN and SLAUGHTER - Nearside", "stop_name": "CULLEN/SLAUGHTER"}, {"stop_lat": 30.169431, "stop_lon": -97.796231, "route_id": "201", "stop_url": "http://www.capmetro.org/gismaps/stops/5380.html", "stop_id": "5380", "stop_desc": "Southwest corner of SLAUGHTER and FRANCIA - Nearside", "stop_name": "SLAUGHTER/FRANCIA"}, {"stop_lat": 30.192663, "stop_lon": -97.777841, "route_id": "201", "stop_url": "http://www.capmetro.org/gismaps/stops/550.html", "stop_id": "550", "stop_desc": "Southwest corner of WILLIAM CANNON and CIRCLE S - Nearside", "stop_name": "115 WILLIAM CANNON/CIRCLE S"}, {"stop_lat": 30.192082, "stop_lon": -97.776037, "route_id": "201", "stop_url": "http://www.capmetro.org/gismaps/stops/551.html", "stop_id": "551", "stop_desc": "Southeast corner of WILLIAM CANNON and CIRCLE S - Mid-Block", "stop_name": "409 WILLIAM CANNON/CIRCLE S"}, {"stop_lat": 30.191387, "stop_lon": -97.77353, "route_id": "201", "stop_url": "http://www.capmetro.org/gismaps/stops/552.html", "stop_id": "552", "stop_desc": "Southeast corner of WILLIAM CANNON and CIRCLE S - Mid-Block", "stop_name": "601 WILLIAM CANNON/CIRCLE S"}, {"stop_lat": 30.192739, "stop_lon": -97.765329, "route_id": "201", "stop_url": "http://www.capmetro.org/gismaps/stops/553.html", "stop_id": "553", "stop_desc": "Southwest corner of NELMS and BLUFF SPRINGS - Nearside", "stop_name": "NELMS/BLUFF SPRINGS"}, {"stop_lat": 30.191773, "stop_lon": -97.774139, "route_id": "201", "stop_url": "http://www.capmetro.org/gismaps/stops/555.html", "stop_id": "555", "stop_desc": "Northwest corner of WILLIAM CANNON and NORTH BLUFF - Mid-Block", "stop_name": "412 WILLIAM CANNON/NORTH BLUFF"}, {"stop_lat": 30.167663, "stop_lon": -97.793747, "route_id": "201", "stop_url": "http://www.capmetro.org/gismaps/stops/5623.html", "stop_id": "5623", "stop_desc": "Southeast corner of SLAUGHTER and SP BACK LOOP - Farside", "stop_name": "205 SLAUGHTER/SP BACK LOOP"}, {"stop_lat": 30.147252, "stop_lon": -97.803199, "route_id": "201", "stop_url": "http://www.capmetro.org/gismaps/stops/5778.html", "stop_id": "5778", "stop_desc": "Northeast corner of 1ST and FM 1626 - Mid-Block", "stop_name": "1ST/FM 1626 (AKINS)"}]
